pysoda/__init__.py
pysoda/cvplus.py
pysoda/guiplus.py
pysoda/pgzplus.py
pysoda-0.0.1.dist-info/METADATA
pysoda-0.0.1.dist-info/WHEEL
pysoda-0.0.1.dist-info/top_level.txt
pysoda-0.0.1.dist-info/RECORD
